libdebuginfod/__init__.py
libdebuginfod/debuginfod.py
pylibdebuginfod-0.3.dist-info/LICENSE.txt
pylibdebuginfod-0.3.dist-info/METADATA
pylibdebuginfod-0.3.dist-info/WHEEL
pylibdebuginfod-0.3.dist-info/top_level.txt
pylibdebuginfod-0.3.dist-info/RECORD
