Metadata-Version: 2.1
Name: pylibdebuginfod
Version: 0.3
Summary: Python bindings for libdebuginfod
Home-page: https://github.com/rupran/pylibdebuginfod
Author: Andreas Ziegler
Author-email: andreas.ziegler@fau.de
License: MIT
Platform: UNKNOWN
Classifier: License :: OSI Approved :: MIT License
Classifier: Topic :: Software Development :: Debuggers
Classifier: Topic :: Software Development :: Libraries :: Python Modules
Classifier: Intended Audience :: Developers
Classifier: Programming Language :: Python :: 3.5
Classifier: Programming Language :: Python :: 3.6
Classifier: Programming Language :: Python :: 3.7
Classifier: Programming Language :: Python :: 3.8
Classifier: Programming Language :: Python :: 3.9
Requires-Dist: pyelftools
